setup.py
package_a8b11/__init__.py
package_a8b11/text.py
package_a8b11.egg-info/PKG-INFO
package_a8b11.egg-info/SOURCES.txt
package_a8b11.egg-info/dependency_links.txt
package_a8b11.egg-info/not-zip-safe
package_a8b11.egg-info/requires.txt
package_a8b11.egg-info/top_level.txt