Metadata-Version: 1.0
Name: package-a8b11
Version: 0.2
Summary: The funniest joke in the world
Home-page: UNKNOWN
Author: David Ivan
Author-email: avandavad@gmail.com
License: MIT
Platform: UNKNOWN
